[
  {
    "date": "2026.07",
    "content": "✈️ Attending IC2S2! 📄 Presenting a parallel talk and a poster, serving as a session chair📍 Burlington, Vermont"
  },
  {
    "date": "2026.04",
    "content": "✈️ Attending CHI'26 in person! 📄 Presenting a paper, serving as SV.📍 Barcelona, Spain"
  },
  {
    "date": "2025.11",
    "content": "🎙 Gave a talk at WikiConference 2025, Seoul."
  },
  {
    "date": "2025.10",
    "content": "✈️ Attending CSCW'25 in person! 📄 Presenting a paper, serving as SV.📍 Bergen, Norway"
  },
  {
    "date": "2025.08",
    "content": "🎙 Gave a general-audience talk titled, <Anxiety in the Technosocial Era: How We Understand and Cope> at CityFarmers."
  },
  {
    "date": "2025.04",
    "content": "📄 Our survey paper is accepted to Journal of Computational Linguistics!"
  },
  {
    "date": "2025.04",
    "content": "📄 Typing Cure paper is accepted to CSCW 2025!"
  },
  {
    "date": "2025.04",
    "content": "✈️ Attending CHI 2025!📄 Presenting a paper, 🤝co-organizing a workshop."
  },
  {
    "date": "2025.04",
    "content": "🐯  I'll be joining Princeton as a PhD student in Fall 2025!"
  },
  {
    "date": "2025.03",
    "content": "✈️ Honored to have received PhD offers from Princeton, U of Washington, U of Michigan, and Georgia Tech. Excited to attend the in-person visit days and decide which path fits best!"
  },
  {
    "date": "2025.01",
    "content": "📄 My first-first-authored NAVER internship paper (ExploreSelf) is accepted to CHI 2025. See you in Yokohama, Japan!"
  },
  {
    "date": "2024.05",
    "content": "✈️ Attending CHI 2024 in-person!🌴 Honolulu, Hawaii"
  },
  {
    "date": "2024.03",
    "content": "🎵 Excited to start my research internship @NAVER AI Lab!"
  },
  {
    "date": "2023.12",
    "content": "✈️ Attending NeurIPS 2023 in person!📍 New Orleans"
  },
  {
    "date": "2023.11",
    "content": "✈️ Attending UIST 2023 in person!📍 San Fransisco"
  },
  {
    "date": "2023.10",
    "content": "👩🏻‍💻 Serving as a Student Volunteer for CSCW'23!📍 Minneapolis"
  },
  {
    "date": "2023.8",
    "content": "🐝 Starting my exchange semester at Georgia Tech. Go Jackets!"
  },
  {
    "date": "2023.5",
    "content": "✈️ Attending CHI'23 in person!📍 Hamburg, Germany"
  }
]